pyytlounge/__init__.py
pyytlounge/api.py
pyytlounge/dial.py
pyytlounge/event_listener.py
pyytlounge/events.py
pyytlounge/exceptions.py
pyytlounge/lounge_models.py
pyytlounge/models.py
pyytlounge/util.py
pyytlounge/wrapper.py
pyytlounge-3.2.0.dist-info/METADATA
pyytlounge-3.2.0.dist-info/WHEEL
pyytlounge-3.2.0.dist-info/licenses/LICENSE
pyytlounge-3.2.0.dist-info/RECORD
