Metadata-Version: 2.4
Name: pyytlounge
Version: 3.2.0
Summary: YouTube Lounge API wrapper
Project-URL: Homepage, https://github.com/FabioGNR/pyytlounge
Project-URL: Bug Tracker, https://github.com/FabioGNR/pyytlounge/issues
Author-email: Fabio <example@example.com>, Berty <example@example.com>
License-File: LICENSE
Classifier: License :: OSI Approved :: MIT License
Classifier: Operating System :: OS Independent
Classifier: Programming Language :: Python :: 3
Requires-Python: >=3.9
Requires-Dist: aiohttp>=3.11.12
Provides-Extra: dev
Requires-Dist: mypy; extra == 'dev'
Requires-Dist: pytest; extra == 'dev'
Requires-Dist: pytest-asyncio; extra == 'dev'
Requires-Dist: pytest-mock; extra == 'dev'
Requires-Dist: ruff; extra == 'dev'
Provides-Extra: docs
Requires-Dist: sphinx; extra == 'docs'
